dnspod_sdk
