Metadata-Version: 1.1
Name: dnspod-sdk
Version: 0.0.2
Summary: A dnspod api SDK
Home-page: https://github.com/codeif/dnspod-sdk
Author: codeif
Author-email: me@codeif.com
License: MIT License
Keywords: DNSPod,DNS,SDK
Platform: UNKNOWN
Classifier: Programming Language :: Python :: 3
